saic_ismart_client_ng/__init__.py
saic_ismart_client_ng/api/__init__.py
saic_ismart_client_ng/api/base.py
saic_ismart_client_ng/api/message/__init__.py
saic_ismart_client_ng/api/message/schema.py
saic_ismart_client_ng/api/schema.py
saic_ismart_client_ng/api/serialization_utils.py
saic_ismart_client_ng/api/user/__init__.py
saic_ismart_client_ng/api/user/schema.py
saic_ismart_client_ng/api/vehicle/__init__.py
saic_ismart_client_ng/api/vehicle/alarm/__init__.py
saic_ismart_client_ng/api/vehicle/alarm/schema.py
saic_ismart_client_ng/api/vehicle/climate/__init__.py
saic_ismart_client_ng/api/vehicle/locks/__init__.py
saic_ismart_client_ng/api/vehicle/locks/schema.py
saic_ismart_client_ng/api/vehicle/schema.py
saic_ismart_client_ng/api/vehicle/windows/__init__.py
saic_ismart_client_ng/api/vehicle/windows/schema.py
saic_ismart_client_ng/api/vehicle_charging/__init__.py
saic_ismart_client_ng/api/vehicle_charging/schema.py
saic_ismart_client_ng/crypto_utils.py
saic_ismart_client_ng/exceptions.py
saic_ismart_client_ng/listener.py
saic_ismart_client_ng/model.py
saic_ismart_client_ng/net/__init__.py
saic_ismart_client_ng/net/client/__init__.py
saic_ismart_client_ng/net/crypto.py
saic_ismart_client_ng/net/httpx/__init__.py
saic_ismart_client_ng/net/utils.py
saic_ismart_client_ng/py.typed
saic_ismart_client_ng-0.9.2.dist-info/LICENSE
saic_ismart_client_ng-0.9.2.dist-info/METADATA
saic_ismart_client_ng-0.9.2.dist-info/WHEEL
saic_ismart_client_ng-0.9.2.dist-info/RECORD
