Metadata-Version: 2.3
Name: saic_ismart_client_ng
Version: 0.9.2
Summary: SAIC next gen client library (MG iSMART)
Author: Giovanni Condello
Author-email: saic-python-client@nanomad.net
Requires-Python: >=3.11
Classifier: Programming Language :: Python :: 3
Classifier: License :: OSI Approved :: MIT License
Classifier: Operating System :: OS Independent
Requires-Dist: dacite (>=1.8.1,<2.0.0)
Requires-Dist: httpx (>=0.27.0,<0.29.0)
Requires-Dist: pycryptodome (>=3.20.0,<4.0.0)
Requires-Dist: tenacity (>=9.0.0,<10.0.0)
Project-URL: Homepage, https://github.com/SAIC-iSmart-API/saic-python-client-ng
Project-URL: Issues, https://github.com/SAIC-iSmart-API/saic-python-client-ng/issues
